dcef/__init__.py
dcef/_frontend.py
dcef/_version.py
dcef/all_transforms.py
dcef/channeldata.json
dcef/configure_utils.py
dcef/dcef_widget.py
dcef/dcf_transform.py
dcef/df_methods.py
dcef/index.html
dcef/lispy.py
dcef/summary_stats.py
dcef/views.py
dcef/labextension/package.json
dcef/labextension/static/116.f2c748ce51e22b52b0cb.js
dcef/labextension/static/116.f2c748ce51e22b52b0cb.js.LICENSE.txt
dcef/labextension/static/250.ca3c9f855fbc1747d0ae.js
dcef/labextension/static/250.ca3c9f855fbc1747d0ae.js.LICENSE.txt
dcef/labextension/static/480.ccd73b95e569f66845e5.js
dcef/labextension/static/486.0708227d0a518f636636.js
dcef/labextension/static/486.0708227d0a518f636636.js.LICENSE.txt
dcef/labextension/static/568.b3c25a51cdf2e2d0b274.js
dcef/labextension/static/remoteEntry.0feae1c557280f564bef.js
dcef/labextension/static/style.js
dcef/labextension/static/third-party-licenses.json
dcef/nbextension/extension.js
dcef/nbextension/index.js
dcef/nbextension/index.js.LICENSE.txt
dcef/noarch/current_repodata.json
dcef/noarch/current_repodata.json.bz2
dcef/noarch/index.html
dcef/noarch/repodata.json
dcef/noarch/repodata.json.bz2
dcef/noarch/repodata_from_packages.json
dcef/noarch/repodata_from_packages.json.bz2
dcef-0.2.5.data/data/share/jupyter/labextensions/dcef/package.json
dcef-0.2.5.data/data/share/jupyter/labextensions/dcef/static/116.f2c748ce51e22b52b0cb.js
dcef-0.2.5.data/data/share/jupyter/labextensions/dcef/static/116.f2c748ce51e22b52b0cb.js.LICENSE.txt
dcef-0.2.5.data/data/share/jupyter/labextensions/dcef/static/250.ca3c9f855fbc1747d0ae.js
dcef-0.2.5.data/data/share/jupyter/labextensions/dcef/static/250.ca3c9f855fbc1747d0ae.js.LICENSE.txt
dcef-0.2.5.data/data/share/jupyter/labextensions/dcef/static/480.ccd73b95e569f66845e5.js
dcef-0.2.5.data/data/share/jupyter/labextensions/dcef/static/486.0708227d0a518f636636.js
dcef-0.2.5.data/data/share/jupyter/labextensions/dcef/static/486.0708227d0a518f636636.js.LICENSE.txt
dcef-0.2.5.dist-info/METADATA
dcef-0.2.5.dist-info/WHEEL
dcef-0.2.5.dist-info/licenses/LICENSE.txt
dcef-0.2.5.dist-info/RECORD
