Metadata-Version: 2.1
Name: dcef
Version: 0.2.5
Summary: Data Cleaning Framework - UI for quickly cleaning pandas dataframes 
Project-URL: Homepage, https://github.com/bloomberg/dcef
Author: Paddy Mullen
License: Copyright (c) 2019 Bloomberg
License-File: LICENSE.txt
Keywords: IPython,Jupyter,Widgets
Classifier: Framework :: Jupyter
Classifier: Intended Audience :: Developers
Classifier: Intended Audience :: Science/Research
Classifier: License :: OSI Approved :: BSD License
Classifier: Programming Language :: Python
Classifier: Programming Language :: Python :: 3
Classifier: Programming Language :: Python :: 3 :: Only
Classifier: Programming Language :: Python :: 3.7
Classifier: Programming Language :: Python :: 3.8
Classifier: Programming Language :: Python :: 3.9
Classifier: Programming Language :: Python :: 3.10
Requires-Python: >=3.7
Requires-Dist: ipywidgets<9,>=7.6.0
Provides-Extra: test
Requires-Dist: nbval>=0.9; extra == 'test'
Requires-Dist: pandas<=1.3.5; extra == 'test'
Requires-Dist: pytest-cov>=3; extra == 'test'
Requires-Dist: pytest>=6; extra == 'test'
